MANIFEST.in
setup.py
orgviz/__init__.py
orgviz/cal.py
orgviz/cli.py
orgviz/default_config.py
orgviz/dones.py
orgviz/event.py
orgviz/graphs.py
orgviz/randomnodes.py
orgviz/sample.py
orgviz/timeline.py
orgviz/web.py
orgviz.egg-info/PKG-INFO
orgviz.egg-info/SOURCES.txt
orgviz.egg-info/dependency_links.txt
orgviz.egg-info/entry_points.txt
orgviz.egg-info/requires.txt
orgviz.egg-info/top_level.txt
orgviz/static/orgviz.js
orgviz/static/timeline.js
orgviz/static/favicons/nuvola/author
orgviz/static/favicons/nuvola/date.ico
orgviz/static/favicons/nuvola/date.png
orgviz/static/favicons/nuvola/kmplot.ico
orgviz/static/favicons/nuvola/kmplot.png
orgviz/static/favicons/nuvola/korganizer.ico
orgviz/static/favicons/nuvola/korganizer.png
orgviz/static/favicons/nuvola/license.txt
orgviz/static/favicons/nuvola/readme.txt
orgviz/static/favicons/nuvola/thanks.to
orgviz/static/lib/colorbox/colorbox.css
orgviz/static/lib/colorbox/index.html
orgviz/static/lib/colorbox/jquery.colorbox-min.js
orgviz/static/lib/colorbox/jquery.colorbox.js
orgviz/static/lib/colorbox/images/border.png
orgviz/static/lib/colorbox/images/controls.png
orgviz/static/lib/colorbox/images/loading_background.png
orgviz/static/lib/colorbox/images/overlay.png
orgviz/static/lib/colorbox/images/ie6/borderBottomCenter.png
orgviz/static/lib/colorbox/images/ie6/borderBottomLeft.png
orgviz/static/lib/colorbox/images/ie6/borderBottomRight.png
orgviz/static/lib/colorbox/images/ie6/borderMiddleLeft.png
orgviz/static/lib/colorbox/images/ie6/borderMiddleRight.png
orgviz/static/lib/colorbox/images/ie6/borderTopCenter.png
orgviz/static/lib/colorbox/images/ie6/borderTopLeft.png
orgviz/static/lib/colorbox/images/ie6/borderTopRight.png
orgviz/static/lib/fullcalendar/GPL-LICENSE.txt
orgviz/static/lib/fullcalendar/MIT-LICENSE.txt
orgviz/static/lib/fullcalendar/fullcalendar.css
orgviz/static/lib/fullcalendar/fullcalendar.js
orgviz/static/lib/fullcalendar/fullcalendar.min.js
orgviz/static/lib/fullcalendar/fullcalendar.print.css
orgviz/static/lib/fullcalendar/gcal.js
orgviz/static/lib/jquery/jquery-1.5.2.min.js
orgviz/static/lib/jquery/jquery-ui-1.8.11.custom.min.js
orgviz/static/lib/jquery/jquery.hotkeys.js
