Metadata-Version: 1.0
Name: orgviz
Version: 0.0.1.dev0
Summary: view org-mode files from different directions
Home-page: https://github.com/tkf/orgviz
Author: Takafumi Arakaki
Author-email: aka.tkf@gmail.com
License: MIT License
Keywords: org,org-mode,Emacs
Platform: UNKNOWN
Classifier: Development Status :: 3 - Alpha
Classifier: Programming Language :: Python
Classifier: Programming Language :: Python :: 2
Classifier: Programming Language :: Python :: 2.6
Classifier: Programming Language :: Python :: 2.7
